tool_inventory/__init__.py
tool_inventory/cli.py
tool_inventory/connections.py
tool_inventory/main.py
tool_inventory/models.py
tool_inventory/py.typed
tool_inventory/routers/__init__.py
tool_inventory/routers/tools.py
tool_inventory/routers/webapp.py
tool_inventory/static/bootstrap.bundle.min.js
tool_inventory/static/bootstrap.min.css
tool_inventory/templates/base.html
tool_inventory/templates/delete_tool.html
tool_inventory/templates/index.html
tool_inventory/templates/tool_form.html
tool_inventory/templates/update_quantity.html
tool_inventory-0.6.0.dist-info/LICENSE
tool_inventory-0.6.0.dist-info/METADATA
tool_inventory-0.6.0.dist-info/WHEEL
tool_inventory-0.6.0.dist-info/entry_points.txt
tool_inventory-0.6.0.dist-info/RECORD
