Metadata-Version: 2.1
Name: tool-inventory
Version: 0.6.0
Summary: Tool inventory.
Home-page: https://github.com/MicaelJarniac/tool-inventory
License: MIT
Author: Micael Jarniac
Author-email: micael@jarniac.dev
Requires-Python: >=3.13,<4.0
Classifier: Development Status :: 1 - Planning
Classifier: License :: OSI Approved :: MIT License
Classifier: Natural Language :: English
Classifier: Operating System :: OS Independent
Classifier: Programming Language :: Python :: 3
Classifier: Programming Language :: Python :: 3.13
Classifier: Typing :: Typed
Requires-Dist: fastapi[standard] (>=0.115.5,<0.116.0)
Requires-Dist: loguru (>=0.7.0,<0.8.0)
Requires-Dist: sqlmodel (>=0.0.22,<0.0.23)
Requires-Dist: thefuzz (>=0.22.1,<0.23.0)
Requires-Dist: typer (>=0.14.0,<0.15.0)
Requires-Dist: uvicorn[standard] (>=0.32.1,<0.33.0)
Project-URL: Bug Tracker, https://github.com/MicaelJarniac/tool-inventory/issues
Project-URL: Changelog, https://github.com/MicaelJarniac/tool-inventory/blob/main/docs/CHANGELOG.md
Project-URL: Documentation, https://tool-inventory.readthedocs.io
Project-URL: Repository, https://github.com/MicaelJarniac/tool-inventory
